{
"type": "FeatureCollection",
"name": "dayFiveEvening",
"crs": { "type": "name", "properties": { "name": "urn:ogc:def:crs:OGC:1.3:CRS84" } },
"features": [
{ "type": "Feature", "properties": { "OBJECTID": 7093, "id": 7466, "building_n": "166800", "lat": 27.42776, "lng": 89.643815, "status": "COMPLETE", "sub_zone_i": 56, "createdAt": "\\N", "updatedAt": "2020-09-22 07:32:38", "POPULATION": 5.0 }, "geometry": { "type": "Point", "coordinates": [ 89.643815, 27.42776 ] } }
]
}
