{
"type": "FeatureCollection",
"name": "dayFour",
"crs": { "type": "name", "properties": { "name": "urn:ogc:def:crs:OGC:1.3:CRS84" } },
"features": [
{ "type": "Feature", "properties": { "id": 9887, "building_n": "169413", "lat": 27.505591, "lng": 89.631429, "status": "COMPLETE", "sub_zone_i": 61, "createdAt": "\\N", "updatedAt": "2020-10-03 04:03:01", "POPULATION": 33.0 }, "geometry": { "type": "Point", "coordinates": [ 89.631429, 27.505591 ] } },
{ "type": "Feature", "properties": { "id": 9903, "building_n": "169429", "lat": 27.505462, "lng": 89.631083, "status": "COMPLETE", "sub_zone_i": 61, "createdAt": "\\N", "updatedAt": "2020-10-02 10:06:39", "POPULATION": 38.0 }, "geometry": { "type": "Point", "coordinates": [ 89.631083, 27.505462 ] } },
{ "type": "Feature", "properties": { "id": 2322, "building_n": "161143", "lat": 27.447955, "lng": 89.66261, "status": "COMPLETE", "sub_zone_i": 24, "createdAt": "\\N", "updatedAt": "2020-10-01 08:55:50", "POPULATION": 0.0 }, "geometry": { "type": "Point", "coordinates": [ 89.66261, 27.447955 ] } },
{ "type": "Feature", "properties": { "id": 5300, "building_n": "164449", "lat": 27.53155, "lng": 89.639778, "status": "COMPLETE", "sub_zone_i": 48, "createdAt": "\\N", "updatedAt": "2020-10-05 04:15:45", "POPULATION": 17.0 }, "geometry": { "type": "Point", "coordinates": [ 89.639778, 27.53155 ] } },
{ "type": "Feature", "properties": { "id": 5326, "building_n": "164475", "lat": 27.529895, "lng": 89.639817, "status": "COMPLETE", "sub_zone_i": 48, "createdAt": "\\N", "updatedAt": "2020-09-30 06:51:29", "POPULATION": 3.0 }, "geometry": { "type": "Point", "coordinates": [ 89.639817, 27.529895 ] } },
{ "type": "Feature", "properties": { "id": 7813, "building_n": "167151", "lat": 27.457748, "lng": 89.642938, "status": "COMPLETE", "sub_zone_i": 51, "createdAt": "\\N", "updatedAt": "2020-10-04 11:07:32", "POPULATION": 61.0 }, "geometry": { "type": "Point", "coordinates": [ 89.642938, 27.457748 ] } },
{ "type": "Feature", "properties": { "id": 8720, "building_n": "168158", "lat": 27.482834, "lng": 89.631565, "status": "COMPLETE", "sub_zone_i": 35, "createdAt": "\\N", "updatedAt": "2020-09-21 09:23:23", "POPULATION": 0.0 }, "geometry": { "type": "Point", "coordinates": [ 89.631565, 27.482834 ] } },
{ "type": "Feature", "properties": { "id": 11152, "building_n": "173522", "lat": 27.472793, "lng": 89.624933, "status": "COMPLETE", "sub_zone_i": 32, "createdAt": "\\N", "updatedAt": "2020-10-05 07:21:41", "POPULATION": 45.0 }, "geometry": { "type": "Point", "coordinates": [ 89.624933, 27.472793 ] } }
]
}
