{
"type": "FeatureCollection",
"name": "dayFourEvening",
"crs": { "type": "name", "properties": { "name": "urn:ogc:def:crs:OGC:1.3:CRS84" } },
"features": [
{ "type": "Feature", "properties": { "OBJECTID": 5440, "id": 5709, "building_n": "164868", "lat": 27.512175, "lng": 89.63656, "status": "COMPLETE", "sub_zone_i": 61, "createdAt": "\\N", "updatedAt": "2020-09-26 09:50:27", "POPULATION": 25.0 }, "geometry": { "type": "Point", "coordinates": [ 89.63656, 27.512175 ] } }
]
}
