{
"type": "FeatureCollection",
"name": "daythirty",
"crs": { "type": "name", "properties": { "name": "urn:ogc:def:crs:OGC:1.3:CRS84" } },
"features": [
{ "type": "Feature", "properties": { "OBJECTID": 3619, "id": 3797, "building_n": "162755", "lat": 27.454985, "lng": 89.656697, "status": "COMPLETE", "sub_zone_i": 36, "createdAt": "\\N", "updatedAt": "2020-09-27 06:58:52", "POPULATION": 19.0 }, "geometry": { "type": "Point", "coordinates": [ 89.656697000000122, 27.454985 ] } },
{ "type": "Feature", "properties": { "OBJECTID": 7982, "id": 8397, "building_n": "167819", "lat": 27.461097, "lng": 89.635227, "status": "COMPLETE", "sub_zone_i": 30, "createdAt": "\\N", "updatedAt": "2020-09-22 11:11:02", "POPULATION": 68.0 }, "geometry": { "type": "Point", "coordinates": [ 89.635227, 27.461097 ] } }
]
}
