{
"type": "FeatureCollection",
"name": "daythreeEvening",
"crs": { "type": "name", "properties": { "name": "urn:ogc:def:crs:OGC:1.3:CRS84" } },
"features": [
{ "type": "Feature", "properties": { "id": 1343, "building_n": "160050", "lat": 27.445482, "lng": 89.66123, "status": "COMPLETE", "sub_zone_i": 17, "createdAt": "\\N", "updatedAt": "2020-09-25 05:47:56", "POPULATION": 118.0 }, "geometry": { "type": "Point", "coordinates": [ 89.66123, 27.445482 ] } },
{ "type": "Feature", "properties": { "id": 5630, "building_n": "164783", "lat": 27.527627, "lng": 89.637928, "status": "COMPLETE", "sub_zone_i": 48, "createdAt": "\\N", "updatedAt": "2020-09-28 05:21:32", "POPULATION": 37.0 }, "geometry": { "type": "Point", "coordinates": [ 89.637928, 27.527627 ] } }
]
}
