{
"type": "FeatureCollection",
"name": "dayThree",
"crs": { "type": "name", "properties": { "name": "urn:ogc:def:crs:OGC:1.3:CRS84" } },
"features": [
{ "type": "Feature", "properties": { "id": 3657, "building_n": "162614", "lat": 27.43707, "lng": 89.655541, "status": "COMPLETE", "sub_zone_i": 2, "createdAt": "\\N", "updatedAt": "2020-10-05 04:09:09", "POPULATION": 80.0 }, "geometry": { "type": "Point", "coordinates": [ 89.655541, 27.43707 ] } },
{ "type": "Feature", "properties": { "id": 4493, "building_n": "163556", "lat": 27.53176, "lng": 89.645007, "status": "COMPLETE", "sub_zone_i": 52, "createdAt": "\\N", "updatedAt": "2020-09-24 08:34:54", "POPULATION": 7.0 }, "geometry": { "type": "Point", "coordinates": [ 89.645007, 27.53176 ] } },
{ "type": "Feature", "properties": { "id": 1343, "building_n": "160050", "lat": 27.445482, "lng": 89.66123, "status": "COMPLETE", "sub_zone_i": 17, "createdAt": "\\N", "updatedAt": "2020-09-25 05:47:56", "POPULATION": 118.0 }, "geometry": { "type": "Point", "coordinates": [ 89.66123, 27.445482 ] } },
{ "type": "Feature", "properties": { "id": 5630, "building_n": "164783", "lat": 27.527627, "lng": 89.637928, "status": "COMPLETE", "sub_zone_i": 48, "createdAt": "\\N", "updatedAt": "2020-09-28 05:21:32", "POPULATION": 37.0 }, "geometry": { "type": "Point", "coordinates": [ 89.637928, 27.527627 ] } },
{ "type": "Feature", "properties": { "id": 7574, "building_n": "166910", "lat": 27.457563, "lng": 89.641431, "status": "COMPLETE", "sub_zone_i": 4, "createdAt": "\\N", "updatedAt": "2020-09-28 09:12:32", "POPULATION": 52.0 }, "geometry": { "type": "Point", "coordinates": [ 89.641431, 27.457563 ] } }
]
}
